poetry_lark/__init__.py
poetry_lark/commands/__init__.py
poetry_lark/commands/command.py
poetry_lark/commands/lark/__init__.py
poetry_lark/commands/lark/add.py
poetry_lark/commands/lark/build.py
poetry_lark/commands/lark/remove.py
poetry_lark/plugin.py
poetry_lark/toml.py
poetry_lark-1.1.0.dist-info/LICENSE
poetry_lark-1.1.0.dist-info/METADATA
poetry_lark-1.1.0.dist-info/WHEEL
poetry_lark-1.1.0.dist-info/entry_points.txt
poetry_lark-1.1.0.dist-info/RECORD
