Metadata-Version: 2.3
Name: poetry-lark
Version: 1.1.0
Summary: Plugin which integrates Lark into the Poetry build system.
License: BSD-2-Clause
Author: Mikhalev Oleg
Author-email: mhalairt@gmail.com
Requires-Python: >=3.9,<4.0
Classifier: Development Status :: 4 - Beta
Classifier: Environment :: Plugins
Classifier: Intended Audience :: Developers
Classifier: License :: OSI Approved :: BSD License
Classifier: Programming Language :: Python :: 3
Classifier: Programming Language :: Python :: 3.9
Classifier: Programming Language :: Python :: 3.10
Classifier: Programming Language :: Python :: 3.11
Classifier: Programming Language :: Python :: 3.12
Classifier: Programming Language :: Python :: 3.13
Classifier: Topic :: Software Development :: Build Tools
Classifier: Topic :: Text Processing
Classifier: Topic :: Utilities
Provides-Extra: interegular
Provides-Extra: regex
Requires-Dist: interegular (>=0.3.1,<0.4.0) ; extra == "interegular"
Requires-Dist: lark (>=1.2.2,<2.0.0)
Requires-Dist: poetry (>=2.1.2,<3.0.0)
Requires-Dist: regex ; extra == "regex"
Project-URL: Repository, https://github.com/mhalairt/poetry-lark
